solargazer/__init__.py
solargazer/solargazer.py
solargazer-0.2.dist-info/LICENSE
solargazer-0.2.dist-info/METADATA
solargazer-0.2.dist-info/WHEEL
solargazer-0.2.dist-info/top_level.txt
solargazer-0.2.dist-info/RECORD
