Metadata-Version: 2.1
Name: solargazer
Version: 0.2
Summary: A simple wrapper for linearmodels to generate clean panel regression tables in LaTeX.
Home-page: https://github.com/elliottmokski/solargazer
Author: Elliott Mokski
Author-email: elliottpmokski@gmail.com
License: UNKNOWN
Platform: UNKNOWN
Requires-Python: >=3.6
Requires-Dist: pandas (>=1.0.0)
Requires-Dist: linearmodels (>=5.0)
